[
  {
    "id": 1596620506,
    "name": "LIFE",
    "folderLink": "C:\\Users\\mdels\\AppData\\Roaming\\gopher\\AppData\\LIFE",
    "CourseShown": true
  },
  {
    "id": 530316479,
    "name": "GMS 7093 Intro Clinical Research",
    "folderLink": "C:\\Users\\mdels\\AppData\\Roaming\\gopher\\AppData\\GMS7093IntroClinicalResearch",
    "CourseShown": false
  },
  {
    "id": 4327007797,
    "name": "Anatomy",
    "folderLink": "C:\\Users\\mdels\\AppData\\Roaming\\gopher\\AppData\\Anatomy",
    "CourseShown": false
  },
  {
    "id": 4990175411,
    "name": "Intro Clinical Medicine",
    "folderLink": "C:\\Users\\mdels\\AppData\\Roaming\\gopher\\AppData\\IntroClinicalMedicine",
    "CourseShown": false
  },
  {
    "id": 8509356974,
    "name": "Genetics",
    "folderLink": "C:\\Users\\mdels\\AppData\\Roaming\\gopher\\AppData\\Genetics",
    "CourseShown": false
  },
  {
    "id": 8450981996,
    "name": "Disco Health",
    "folderLink": "C:\\Users\\mdels\\AppData\\Roaming\\gopher\\AppData\\DiscoHealth",
    "CourseShown": false
  },
  {
    "id": 1217876399,
    "name": "Health System Science",
    "folderLink": "C:\\Users\\mdels\\AppData\\Roaming\\gopher\\AppData\\HealthSystemScience",
    "CourseShown": false
  },
  {
    "id": 6638113133,
    "name": "Foundations of Medicine",
    "folderLink": "C:\\Users\\mdels\\AppData\\Roaming\\gopher\\AppData\\FoundationsofMedicine",
    "CourseShown": false
  },
  {
    "id": 2471165808,
    "name": "Khalifa Lab",
    "folderLink": "C:\\Users\\mdels\\AppData\\Roaming\\gopher\\AppData\\KhalifaLab",
    "CourseShown": true
  },
  {
    "id": 6361401678,
    "name": "Lucke Wold",
    "folderLink": "C:\\Users\\mdels\\AppData\\Roaming\\gopher\\AppData\\LuckeWold",
    "CourseShown": false
  },
  {
    "id": 3574937320,
    "name": "CRP",
    "folderLink": "C:\\Users\\mdels\\AppData\\Roaming\\gopher\\AppData\\CRP",
    "CourseShown": true
  },
  {
    "id": 4564765838,
    "name": "PFF",
    "folderLink": "C:\\Users\\mdels\\AppData\\Roaming\\gopher\\AppData\\PFF",
    "CourseShown": false
  },
  {
    "id": 2056997574,
    "name": "Nutrition",
    "folderLink": "C:\\Users\\mdels\\AppData\\Roaming\\gopher\\AppData\\Nutrition",
    "CourseShown": false
  },
  {
    "id": 4970001511,
    "name": "Principe Lab",
    "folderLink": "C:\\Users\\mdels\\AppData\\Roaming\\gopher\\AppData\\PrincipeLab",
    "CourseShown": false
  },
  {
    "id": 7987585705,
    "name": "Fun-ology",
    "folderLink": "C:\\Users\\mdels\\AppData\\Roaming\\gopher\\AppData\\Fun-ology",
    "CourseShown": false
  },
  {
    "id": 3440106517,
    "name": "EMT Recert",
    "folderLink": "C:\\Users\\mdels\\AppData\\Roaming\\gopher\\AppData\\EMTRecert",
    "CourseShown": false
  },
  {
    "id": 1896753703,
    "name": "LAC",
    "folderLink": "C:\\Users\\mdels\\AppData\\Roaming\\gopher\\AppData\\LAC",
    "CourseShown": true
  },
  {
    "id": 5376133843,
    "name": "CABBAGE",
    "folderLink": "C:\\Users\\mdels\\AppData\\Roaming\\gopher\\AppData\\CABBAGE",
    "CourseShown": false
  },
  {
    "id": 3140657235,
    "name": "Lungs",
    "folderLink": "C:\\Users\\mdels\\AppData\\Roaming\\gopher\\AppData\\Lungs",
    "CourseShown": false
  },
  {
    "id": 8649305971,
    "name": "Cardio",
    "folderLink": "C:\\Users\\mdels\\AppData\\Roaming\\gopher\\AppData\\Cardio",
    "CourseShown": false
  },
  {
    "id": 1791568977,
    "name": "Renal",
    "folderLink": "C:\\Users\\mdels\\AppData\\Roaming\\gopher\\AppData\\Renal",
    "CourseShown": false
  },
  {
    "id": 7163867942,
    "name": "Summer Dissections",
    "folderLink": "C:\\Users\\mdels\\AppData\\Roaming\\gopher\\AppData\\SummerDissections",
    "CourseShown": false
  },
  {
    "id": 7163867943,
    "name": "Vemuri Lab",
    "folderLink": "C:\\Users\\mdels\\AppData\\Roaming\\gopher\\AppData\\VemuriLab",
    "CourseShown": false
  },
  {
    "id": 7163867944,
    "name": "MSK",
    "folderLink": "C:\\Users\\mdels\\AppData\\Roaming\\gopher\\AppData\\MSK",
    "CourseShown": false
  },
  {
    "id": 7163867945,
    "name": "STEP",
    "folderLink": "C:\\Users\\mdels\\AppData\\Roaming\\gopher\\AppData\\STEP",
    "CourseShown": false
  },
  {
    "id": 7163867946,
    "name": "ICM2",
    "folderLink": "C:\\Users\\mdels\\AppData\\Roaming\\gopher\\AppData\\ICM2",
    "CourseShown": false
  },
  {
    "id": 7163867947,
    "name": "Rohen Anatomy",
    "folderLink": "C:\\Users\\mdels\\AppData\\Roaming\\gopher\\AppData\\RohenAnatomy",
    "CourseShown": true
  },
  {
    "id": 7163867948,
    "name": "Neuro",
    "folderLink": "C:\\Users\\mdels\\AppData\\Roaming\\gopher\\AppData\\Neuro",
    "CourseShown": false
  },
  {
    "id": 71638679498,
    "name": "Pain",
    "folderLink": "C:\\Users\\mdels\\AppData\\Roaming\\gopher\\AppData\\Pain",
    "CourseShown": false
  },
  {
    "id": 71638679499,
    "name": "GI",
    "folderLink": "C:\\Users\\mdels\\AppData\\Roaming\\gopher\\AppData\\GI",
    "CourseShown": false
  },
  {
    "id": 71638679500,
    "name": "Oweiss Lab",
    "folderLink": "C:\\Users\\mdels\\AppData\\Roaming\\gopher\\AppData\\OweissLab",
    "CourseShown": true
  }
  ,
  {
    "id": 71638679501,
    "name": "Medical School",
    "folderLink": "C:\\Users\\mdels\\AppData\\Roaming\\gopher\\AppData\\MedicalSchool",
    "CourseShown": true
  }
  ,
  {
    "id": 71638679502,
    "name": "Lab Work",
    "folderLink": "C:\\Users\\mdels\\AppData\\Roaming\\gopher\\AppData\\LabWork",
    "CourseShown": true
  }
]